{"cameraMode":{"drawMode":0,"name":"Shaded","section":"Shading Mode"},"sceneLighting":false,"audioPlay":false,"sceneViewState":{"m_AlwaysRefresh":false,"showFog":true,"showSkybox":false,"showFlares":true,"showImageEffects":true,"showParticleSystems":true,"showVisualEffectGraphs":true,"m_FxEnabled":true},"in2DMode":false,"pivot":{"x":-2.809999942779541,"y":0.5,"z":0.0},"rotation":{"x":0.6002606749534607,"y":0.03117113560438156,"z":-0.02342206798493862,"w":0.7988535165786743},"size":0.6807264685630798,"orthographic":false}